{
  "routes": [
    {
      "method": "GET",
      "path": "/dummies",
      "handler": "dummy.find",
      "config": {
        "policies": []
      }
    },
    {
      "method": "GET",
      "path": "/dummies/count",
      "handler": "dummy.count",
      "config": {
        "policies": []
      }
    },
    {
      "method": "GET",
      "path": "/dummies/:id",
      "handler": "dummy.findOne",
      "config": {
        "policies": []
      }
    },
    {
      "method": "POST",
      "path": "/dummies",
      "handler": "dummy.create",
      "config": {
        "policies": []
      }
    },
    {
      "method": "PUT",
      "path": "/dummies/:id",
      "handler": "dummy.update",
      "config": {
        "policies": []
      }
    },
    {
      "method": "DELETE",
      "path": "/dummies/:id",
      "handler": "dummy.delete",
      "config": {
        "policies": []
      }
    }
  ]
}
